<root><text><body>
<div><pb n="1" facs="#facs_78_253-1.jpg"/><div><lb/>Brief 43.                   Espol, den 23.1.48.
<lb/>Mein lieber guter Karl, mein liebster Vati!
<lb/>Viele liebe herzliche Grüße senden wir Dir lieber
<lb/>Vati. Wir fahren eben jeden Tag Schlitten. Mutti
<lb/>fährt auch mit, weißt Du Reinhart allein kann
<lb/>ich nicht fahren lassen, er ist doch oft so wackelig.
<lb/>Heute Nachmittag waren wir mal bei
<lb/>Hennens klönen. Reinhart geht gerne nach
<lb/>Hennens u dann sind wir hinter dem Dorf
<lb/>runter gefahren. Jetzt ist es doch noch richtig
<lb/>Winter geworden, wir haben viel Schnee u
<lb/>es schneit noch immer. Vater war heute
<lb/>nach Northeim, Hennens waren mit dem
<lb/>Wagen hin, Kohlen u Eisen holen. Vater ist aber
<lb/>mit Willi mit der Bahn gefahren. Weißt Du
<lb/>Karl, Vater hat heute 3 Meter Klavierband
<lb/>weißt Du richtig Messing wie es in unserm
<lb/>Schrank ist bekommen. Wir hatten schon so
<lb/>viel darum gefragt, aber heute hat es
<lb/>zum ersten mal geklappt. So allmählich
<lb/>kriegen wir doch was zusammen.
<lb/>Post haben wir von Dir noch keine wieder
<lb/>bekommen, ich denke es trifft doch bald
<lb/>mal wieder 1 Schiff ein was uns Briefe
<lb/>mitbringt.
<lb/>
<lb/>Morgen soll ich nach Moringen, Gustavs Hose
<lb/>vom Schneider abholen. Gustav hat sich Vaters
<lb/>braune Stiefelhose blau färben lassen u
<lb/>hat sie sich bei Heine umändern lassen.
<lb/>Morgen gehe ich auf dem Rückweg auch mal
<lb/>bei Emmi u Ernst vor. Hast Du ihnen schon
<lb/>mal geschrieben? Liebster Karl ich weiß heute
<lb/>Abend keine große Neuigkeiten, am
<lb/>Sonntag schreibe ich dir wieder mehr.
<lb/>Für heute   Abend Dir alles gute u viele
<lb/>liebste herzliche Grüße u liebste Bussel
<lb/>Deine Else u Reinhart.
<lb/>
<lb/>Alle lassen Dich recht herzlich
<lb/>grüßen.
</div>
</div></body>
</text></root>